lsHotword/HDatagen.py
lsHotword/HTrainer.py
lsHotword/__init__.py
lsHotword/chime.wav
lsHotword/funcHDatagen.py
lsHotword/funcHTrainer.py
lsHotword/funcHfTrainModel.py
lsHotword/hotword.py
lsHotword/ls.py
lsHotword/lsrc.py
lsHotword/uitrainer.py
lsHotword-1.2.4.dist-info/LICENSE
lsHotword-1.2.4.dist-info/METADATA
lsHotword-1.2.4.dist-info/WHEEL
lsHotword-1.2.4.dist-info/entry_points.txt
lsHotword-1.2.4.dist-info/top_level.txt
lsHotword-1.2.4.dist-info/RECORD
