Metadata-Version: 2.1
Name: lsHotword
Version: 1.2.4
Summary: Hotword/Wake Word detection in python for all platforms(Windows/Linux/Mac).
Home-page: https://github.com/HemantKArya/lsHotword
Download-URL: 
Author: Hemant Kumar
Author-email: iamhemantindia@protonmail.com
License: MIT
Keywords: hotword,detector,lshotword,windows,python,wake word,wake-word,detection
License-File: LICENSE
Requires-Dist: matplotlib
Requires-Dist: numpy
Requires-Dist: pydub
Requires-Dist: pyaudio
Requires-Dist: tensorflow
Requires-Dist: scipy
Requires-Dist: pyqt6
